nyx_kaggle_manager/__init__.py
nyx_kaggle_manager/nyxcli.py
nyx_kaggle_manager/lib/__init__.py
nyx_kaggle_manager/lib/inspector.py
nyx_kaggle_manager/lib/logger.py
nyx_kaggle_manager/lib/schemas.py
nyx_kaggle_manager/lib/utils.py
nyx_kaggle_manager/local/__init__.py
nyx_kaggle_manager/local/kaggle_adapter.py
nyx_kaggle_manager/local/local_mcp.py
nyx_kaggle_manager/local/scheduler.py
nyx_kaggle_manager/remote/__init__.py
nyx_kaggle_manager/remote/network_manager.py
nyx_kaggle_manager/remote/workers_runner.py
nyxai_cli-4.0.7.dist-info/METADATA
nyxai_cli-4.0.7.dist-info/WHEEL
nyxai_cli-4.0.7.dist-info/entry_points.txt
nyxai_cli-4.0.7.dist-info/top_level.txt
nyxai_cli-4.0.7.dist-info/RECORD
