Metadata-Version: 2.1
Name: nyxai-cli
Version: 4.0.7
Summary: Nyx AI Tools CLI
Author: Nyx AI Tools
Requires-Python: >=3.7
Requires-Dist: kaggle>=1.6.0
Requires-Dist: pyyaml>=6.0
Requires-Dist: psutil>=6.0.0
Requires-Dist: requests>=2.31.0
Requires-Dist: aiohttp>=3.9.0
